AUTHORS.rst
CONTRIBUTING.rst
LICENSE
MANIFEST.in
README.rst
setup.cfg
setup.py
djangocms_forms/__init__.py
djangocms_forms/admin.py
djangocms_forms/apps.py
djangocms_forms/cms_app.py
djangocms_forms/cms_apps.py
djangocms_forms/cms_plugins.py
djangocms_forms/compat.py
djangocms_forms/conf.py
djangocms_forms/fields.py
djangocms_forms/forms.py
djangocms_forms/managers.py
djangocms_forms/models.py
djangocms_forms/signals.py
djangocms_forms/uploads.py
djangocms_forms/urls.py
djangocms_forms/utils.py
djangocms_forms/views.py
djangocms_forms/widgets.py
djangocms_forms.egg-info/PKG-INFO
djangocms_forms.egg-info/SOURCES.txt
djangocms_forms.egg-info/dependency_links.txt
djangocms_forms.egg-info/not-zip-safe
djangocms_forms.egg-info/requires.txt
djangocms_forms.egg-info/top_level.txt
djangocms_forms/migrations/0001_initial.py
djangocms_forms/migrations/0002_alter_model_options.py
djangocms_forms/migrations/0003_add_referrer_field.py
djangocms_forms/migrations/0004_redirect_delay.py
djangocms_forms/migrations/0005_formfield_field_name.py
djangocms_forms/migrations/__init__.py
djangocms_forms/south_migrations/0001_initial.py
djangocms_forms/south_migrations/0002_auto__add_field_formsubmission_referrer.py
djangocms_forms/south_migrations/0003_auto_add_redirect_delay.py
djangocms_forms/south_migrations/__init__.py
djangocms_forms/static/css/djangocms_forms/admin/djangocms_forms.css
djangocms_forms/static/js/djangocms_forms/jquery.djangocms-forms.js
djangocms_forms/static/js/djangocms_forms/admin/jquery-form-export.js
djangocms_forms/static/js/djangocms_forms/admin/jquery-inline-collapsible.js
djangocms_forms/static/js/djangocms_forms/admin/jquery-inline-positioning.js
djangocms_forms/static/js/djangocms_forms/admin/jquery-inline-rename.js
djangocms_forms/static/js/djangocms_forms/admin/jquery-inline-toggle-fields.js
djangocms_forms/static/js/djangocms_forms/libs/jquery-ui.min.js
djangocms_forms/static/js/djangocms_forms/libs/jquery.form.min.js
djangocms_forms/static/js/djangocms_forms/libs/jquery.min.js
djangocms_forms/templates/admin/djangocms_forms/formsubmission/change_form.html
djangocms_forms/templates/admin/djangocms_forms/formsubmission/change_list.html
